flask_caslite/__init__.py
flask_caslite/cas.py
Flask_CasLite-0.0.1.dist-info/LICENSE
Flask_CasLite-0.0.1.dist-info/METADATA
Flask_CasLite-0.0.1.dist-info/WHEEL
Flask_CasLite-0.0.1.dist-info/top_level.txt
Flask_CasLite-0.0.1.dist-info/RECORD
